dxitemspy/DXCCSR-Reference-File-v2023-1.xlsx
dxitemspy/DXI_Labels_v2021.1.xlsx
dxitemspy/ICD_10_CM_to_DXI_Mapping_v2021.1.xlsx
dxitemspy/Valid Procedure Codes v2.xlsx
dxitemspy/Z_DXI_Model1_P_AnnTotalSpend_250K.sas
dxitemspy/__about__.py
dxitemspy/__init__.py
dxitemspy/dxi_mapping.json
dxitemspy/dxi_metadata.json
dxitemspy/dxitems.py
dxitemspy/parse_dxi_mapping.py
dxitemspy/parse_dxi_meta.py
dxitemspy-0.0.5.dist-info/METADATA
dxitemspy-0.0.5.dist-info/WHEEL
dxitemspy-0.0.5.dist-info/licenses/LICENSE.txt
dxitemspy-0.0.5.dist-info/RECORD
