Metadata-Version: 2.1
Name: dxitemspy
Version: 0.0.5
Project-URL: Documentation, https://github.com/yubin-park/dxitemspy#readme
Project-URL: Issues, https://github.com/yubin-park/dxitemspy/issues
Project-URL: Source, https://github.com/yubin-park/dxitemspy
Author-email: yubin-park <yubin.park@gmail.com>
License-Expression: MIT
License-File: LICENSE.txt
Classifier: Development Status :: 4 - Beta
Classifier: Programming Language :: Python
Classifier: Programming Language :: Python :: 3.7
Classifier: Programming Language :: Python :: 3.8
Classifier: Programming Language :: Python :: 3.9
Classifier: Programming Language :: Python :: 3.10
Classifier: Programming Language :: Python :: 3.11
Classifier: Programming Language :: Python :: Implementation :: CPython
Classifier: Programming Language :: Python :: Implementation :: PyPy
Requires-Python: >=3.7
